pythesyncer/__init__.py
pythesyncer/auth.py
pythesyncer-23.12.21.18.dist-info/METADATA
pythesyncer-23.12.21.18.dist-info/WHEEL
pythesyncer-23.12.21.18.dist-info/entry_points.txt
pythesyncer-23.12.21.18.dist-info/top_level.txt
pythesyncer-23.12.21.18.dist-info/RECORD
