Metadata-Version: 2.1
Name: pythesyncer
Version: 23.12.21.18
Summary: PythonTheSyncer
Home-page: https://github.com/private_repo/
Author: john
Author-email: john@gmail.com
Classifier: Programming Language :: Python :: 3
Classifier: License :: OSI Approved :: MIT License
Classifier: Operating System :: OS Independent
Requires-Dist: codefast
Requires-Dist: fire
Requires-Dist: boto3
Requires-Dist: rich
Requires-Dist: aiohttp
Requires-Dist: simauth
